fastmcp/__init__.py
fastmcp/exceptions.py
fastmcp/mcp_config.py
fastmcp/py.typed
fastmcp/settings.py
fastmcp/cli/__init__.py
fastmcp/cli/claude.py
fastmcp/cli/cli.py
fastmcp/cli/run.py
fastmcp/cli/install/__init__.py
fastmcp/cli/install/claude_code.py
fastmcp/cli/install/claude_desktop.py
fastmcp/cli/install/cursor.py
fastmcp/cli/install/mcp_json.py
fastmcp/cli/install/shared.py
fastmcp/client/__init__.py
fastmcp/client/client.py
fastmcp/client/elicitation.py
fastmcp/client/logging.py
fastmcp/client/messages.py
fastmcp/client/oauth_callback.py
fastmcp/client/progress.py
fastmcp/client/roots.py
fastmcp/client/sampling.py
fastmcp/client/transports.py
fastmcp/client/auth/__init__.py
fastmcp/client/auth/bearer.py
fastmcp/client/auth/oauth.py
fastmcp/contrib/README.md
fastmcp/contrib/bulk_tool_caller/README.md
fastmcp/contrib/bulk_tool_caller/__init__.py
fastmcp/contrib/bulk_tool_caller/bulk_tool_caller.py
fastmcp/contrib/bulk_tool_caller/example.py
fastmcp/contrib/component_manager/README.md
fastmcp/contrib/component_manager/__init__.py
fastmcp/contrib/component_manager/component_manager.py
fastmcp/contrib/component_manager/component_service.py
fastmcp/contrib/component_manager/example.py
fastmcp/contrib/mcp_mixin/README.md
fastmcp/contrib/mcp_mixin/__init__.py
fastmcp/contrib/mcp_mixin/example.py
fastmcp/contrib/mcp_mixin/mcp_mixin.py
fastmcp/experimental/sampling/__init__.py
fastmcp/experimental/sampling/handlers/__init__.py
fastmcp/experimental/sampling/handlers/base.py
fastmcp/experimental/sampling/handlers/openai.py
fastmcp/experimental/server/openapi/README.md
fastmcp/experimental/server/openapi/__init__.py
fastmcp/experimental/server/openapi/components.py
fastmcp/experimental/server/openapi/routing.py
fastmcp/experimental/server/openapi/server.py
fastmcp/experimental/utilities/openapi/README.md
fastmcp/experimental/utilities/openapi/__init__.py
fastmcp/experimental/utilities/openapi/director.py
fastmcp/experimental/utilities/openapi/formatters.py
fastmcp-2.12.1.dist-info/METADATA
fastmcp-2.12.1.dist-info/WHEEL
fastmcp-2.12.1.dist-info/entry_points.txt
fastmcp-2.12.1.dist-info/licenses/LICENSE
fastmcp-2.12.1.dist-info/RECORD
